gw_eccentricity/__init__.py
gw_eccentricity/compare_methods.py
gw_eccentricity/eccDefinition.py
gw_eccentricity/eccDefinitionUsingAmplitude.py
gw_eccentricity/eccDefinitionUsingAmplitudeFits.py
gw_eccentricity/eccDefinitionUsingFrequency.py
gw_eccentricity/eccDefinitionUsingFrequencyFits.py
gw_eccentricity/eccDefinitionUsingResidualAmplitude.py
gw_eccentricity/eccDefinitionUsingResidualFrequency.py
gw_eccentricity/gw_eccentricity.py
gw_eccentricity/load_data.py
gw_eccentricity/plot_settings.py
gw_eccentricity/truncate_waveform_by_flow.py
gw_eccentricity/utils.py
gw_eccentricity-2.0.0.dist-info/licenses/LICENSE
gw_eccentricity-2.0.0.dist-info/METADATA
gw_eccentricity-2.0.0.dist-info/WHEEL
gw_eccentricity-2.0.0.dist-info/top_level.txt
gw_eccentricity-2.0.0.dist-info/RECORD
