Metadata-Version: 2.4
Name: gw_eccentricity
Version: 2.0.0
Summary: Defining eccentricity for gravitational wave astronomy.
Home-page: https://github.com/vijayvarma392/gw_eccentricity
Author: Md Arif Shaikh, Vijay Varma, Harald Pfeiffer
Author-email: arifshaikh.astro@gmail.com, vijay.varma392@gmail.com
Keywords: black-holes gravitational-waves
Classifier: Intended Audience :: Science/Research
Classifier: Natural Language :: English
Classifier: Topic :: Scientific/Engineering :: Physics
Classifier: Topic :: Scientific/Engineering :: Astronomy
Classifier: License :: OSI Approved :: MIT License
Classifier: Programming Language :: Python
Classifier: Operating System :: OS Independent
License-File: LICENSE
Requires-Dist: numpy
Requires-Dist: scipy
Requires-Dist: h5py
Requires-Dist: lalsuite
Requires-Dist: sxs
Requires-Dist: scri
Requires-Dist: polyrat
Dynamic: author
Dynamic: author-email
Dynamic: classifier
Dynamic: description
Dynamic: description-content-type
Dynamic: home-page
Dynamic: keywords
Dynamic: license-file
Dynamic: requires-dist
Dynamic: summary
